{"categorical": {"sub_grade": ["A1", "A2", "A3", "A4", "A5", "B1", "B2", "B3", "B4", "B5", "C1", "C2", "C3", "C4", "C5", "D1", "D2", "D3", "D4", "D5", "E1", "E2", "E3", "E4", "E5", "F1", "F2", "F3", "F4", "F5", "G1", "G2", "G3", "G4", "G5"], "home_ownership": ["ANY", "MORTGAGE", "NONE", "OWN", "RENT"], "purpose": ["car", "credit_card", "debt_consolidation", "educational", "home_improvement", "house", "major_purchase", "medical", "moving", "other", "renewable_energy", "small_business", "vacation", "wedding"], "application_type": ["Individual", "Joint App"], "verification_status": ["Not Verified", "Source Verified", "Verified"], "addr_state": ["AK", "AL", "AR", "AZ", "CA", "CO", "CT", "DC", "DE", "FL", "GA", "HI", "IA", "ID", "IL", "IN", "KS", "KY", "LA", "MA", "MD", "ME", "MI", "MN", "MO", "MS", "MT", "NC", "ND", "NE", "NH", "NJ", "NM", "NV", "NY", "OH", "OK", "OR", "PA", "RI", "SC", "SD", "TN", "TX", "UT", "VA", "VT", "WA", "WI", "WV", "WY"], "initial_list_status": ["f", "w"]}, "numerical": {"term": {"min": 3.0, "max": 5.0, "default": 3.0}, "fico_range_low": {"min": 660.0, "max": 845.0, "default": 690.0}, "total_acc": {"min": 2.0, "max": 169.0, "default": 23.0}, "pub_rec": {"min": 0.0, "max": 86.0, "default": 0.0}, "revol_util": {"min": 0.0, "max": 100.0, "default": 50.5}, "annual_inc": {"min": 0.0, "max": 231084.0, "default": 65000.0}, "int_rate": {"min": 5.31, "max": 34.289915042481, "default": 12.39}, "dti": {"min": 0.0, "max": 60.0, "default": 17.83}, "mort_acc": {"min": 0.0, "max": 37.0, "default": 1.0}, "loan_amnt": {"min": 1000.0, "max": 40000.0, "default": 12000.0}, "installment": {"min": 14.77, "max": 1569.11, "default": 369.54}, "pub_rec_bankruptcies": {"min": 0.0, "max": 9.0, "default": 0.0}, "fico_range_high": {"min": 664.0, "max": 850.0, "default": 694.0}, "revol_bal": {"min": 0.0, "max": 882984.0, "default": 10842.0}, "open_acc": {"min": 0.0, "max": 76.0, "default": 11.0}, "emp_length": {"min": 0.0, "max": 11.0, "default": 6.0}, "time_to_earliest_cr_line": {"min": 97113.6, "max": 1491177.6, "default": 470707.2}, "issue_year": {"min": 2014.0, "max": 2018.0, "default": 2015.0}, "issue_month": {"min": 1.0, "max": 12.0, "default": 6.0}}, "outlier_bounds": {"annual_inc": {"lower": -86000.0, "upper": 222000.0}, "int_rate": {"lower": -10.089999999999998, "upper": 34.849999999999994}, "time_to_earliest_cr_line": {"lower": -486518.40000000014, "upper": 1483315.2000000002}}, "mappings": {"term": ["36 months", "60 months"]}}